{
    "type": "bundle",
    "id": "bundle--f6876e1a-d2c2-4e25-b051-e95df34fa3d4",
    "objects": [
        {
            "type": "relationship",
            "spec_version": "2.1",
            "id": "relationship--3269d840-c766-4964-9cf2-3e94faf86e8b",
            "created_by_ref": "identity--b73c59c1-8560-449a-b8d0-c2ce0533c5bf",
            "created": "2024-11-18T16:43:42.497312Z",
            "modified": "2024-11-18T16:43:42.497312Z",
            "relationship_type": "uses",
            "description": "Lateral Movement::Ingress Tool Transfer (T1105) --  GoBotKR attempts to copy itself into public folders of cloud storage services (Google Drive, Dropbox, OneDrive). [1]",
            "source_ref": "malware--1d7510c2-1f49-4a7b-96fd-a493a37e8819",
            "target_ref": "attack-pattern--e6919abc-99f9-4c6c-95a5-14761e7b2add",
            "object_marking_refs": [
                "marking-definition--093b6375-cd45-4aa3-8f91-6a03ddd7a3d3"
            ]
        }
    ]
}