{
    "type": "bundle",
    "id": "bundle--81f8d329-cd5b-4d95-a77d-587fd5fca13c",
    "objects": [
        {
            "type": "relationship",
            "spec_version": "2.1",
            "id": "relationship--026dc104-2ad7-49e4-915f-9f72e6e75bfd",
            "created_by_ref": "identity--b73c59c1-8560-449a-b8d0-c2ce0533c5bf",
            "created": "2024-11-18T16:43:37.559131Z",
            "modified": "2024-11-18T16:43:37.559131Z",
            "relationship_type": "uses",
            "description": "Impact::Remote Access (B0022) -- After the Poison Ivy server is running on the target machine, the attacker uses a Windows GUI client to control the target computer. [1]",
            "source_ref": "malware--f68cd3e5-afa7-48ef-bba0-11c58ab8026f",
            "target_ref": "malware-behavior--b41aeeb5-d38d-48e0-b94f-49b13c094c28",
            "object_marking_refs": [
                "marking-definition--093b6375-cd45-4aa3-8f91-6a03ddd7a3d3"
            ]
        }
    ]
}