{
    "type": "bundle",
    "id": "bundle--cc36b802-c583-4db7-96d0-570e5b660672",
    "objects": [
        {
            "type": "relationship",
            "spec_version": "2.1",
            "id": "relationship--b86f3106-e004-46fe-a413-24d4cc8b30af",
            "created_by_ref": "identity--b73c59c1-8560-449a-b8d0-c2ce0533c5bf",
            "created": "2024-02-26T17:04:50.03593Z",
            "modified": "2024-02-26T17:04:50.03593Z",
            "relationship_type": "uses",
            "description": "Defense Evasion::Hijack Execution Flow::Abuse Windows Function Calls (F0015.006) -- Malware escalates privileges by impersonating the token through using LogonUser and ImpersonateLoggedOnUser then ImpersonateNamedPipeClient. [2]",
            "source_ref": "malware--d5ea76ff-a298-4ffa-a30e-458e64fcf78d",
            "target_ref": "malware-method--d9603f75-8c52-4ed7-94f9-bccee293de61",
            "object_marking_refs": [
                "marking-definition--093b6375-cd45-4aa3-8f91-6a03ddd7a3d3"
            ]
        }
    ]
}