{
    "type": "bundle",
    "id": "bundle--d875c8f3-bda7-484c-ac1c-d78a229739f0",
    "objects": [
        {
            "type": "indicator",
            "spec_version": "2.1",
            "id": "indicator--968f5dfa-d4e1-48b3-9b7c-a0d0a22d30cd",
            "created_by_ref": "identity--b73c59c1-8560-449a-b8d0-c2ce0533c5bf",
            "created": "2024-02-26T17:04:47.13022Z",
            "modified": "2024-02-26T17:04:47.13022Z",
            "name": "Ursnif URL",
            "description": "This is an IoC for Ursnif",
            "indicator_types": [
                "malicious-activity"
            ],
            "pattern": "[ url:value = 'hxxp://62.138.9[.]11/vnc32.dll' ]",
            "pattern_type": "stix",
            "pattern_version": "2.1",
            "valid_from": "2024-02-26T17:04:47.13022Z",
            "object_marking_refs": [
                "marking-definition--093b6375-cd45-4aa3-8f91-6a03ddd7a3d3"
            ]
        }
    ]
}