{
    "type": "bundle",
    "id": "bundle--bbae294f-43a7-4f57-ac82-0ffe1a5d4d6e",
    "objects": [
        {
            "type": "indicator",
            "spec_version": "2.1",
            "id": "indicator--9d2ef995-4887-4aa5-b6d4-c7e3f451f2e4",
            "created_by_ref": "identity--b73c59c1-8560-449a-b8d0-c2ce0533c5bf",
            "created": "2024-11-18T16:43:40.344334Z",
            "modified": "2024-11-18T16:43:40.344334Z",
            "name": "Geneio hash",
            "description": "This is an IoC for Geneio",
            "indicator_types": [
                "malicious-activity"
            ],
            "pattern": "[ file:hashes.'SHA-256' = '56b1d33fde65ab520a6c8afe9b3f304c50b581d3e46a9baa56fb9694d4d7effc' ]",
            "pattern_type": "stix",
            "pattern_version": "2.1",
            "valid_from": "2024-11-18T16:43:40.344334Z",
            "object_marking_refs": [
                "marking-definition--093b6375-cd45-4aa3-8f91-6a03ddd7a3d3"
            ]
        }
    ]
}